{
  "signs": [
    {
      "id": "aries",
      "name": "Овен",
      "symbol": "♈",
      "dates": "21 марта – 19 апреля",
      "description": "Смелый, решительный, энергичный",
      "color": "#FF4D4D"
    },
    {
      "id": "taurus",
      "name": "Телец",
      "symbol": "♉",
      "dates": "20 апреля – 20 мая",
      "description": "Надёжный, терпеливый, практичный",
      "color": "#4CAF50"
    },
    {
      "id": "gemini",
      "name": "Близнецы",
      "symbol": "♊",
      "dates": "21 мая – 20 июня",
      "description": "Общительный, любознательный, адаптивный",
      "color": "#FFC107"
    },
    {
      "id": "cancer",
      "name": "Рак",
      "symbol": "♋",
      "dates": "21 июня – 22 июля",
      "description": "Чуткий, заботливый, интуитивный",
      "color": "#00BCD4"
    },
    {
      "id": "leo",
      "name": "Лев",
      "symbol": "♌",
      "dates": "23 июля – 22 августа",
      "description": "Щедрый, творческий, лидерский",
      "color": "#FF9800"
    },
    {
      "id": "virgo",
      "name": "Дева",
      "symbol": "♍",
      "dates": "23 августа – 22 сентября",
      "description": "Аналитичный, практичный, внимательный",
      "color": "#8BC34A"
    },
    {
      "id": "libra",
      "name": "Весы",
      "symbol": "♎",
      "dates": "23 сентября – 22 октября",
      "description": "Дипломатичный, гармоничный, справедливый",
      "color": "#E91E63"
    },
    {
      "id": "scorpio",
      "name": "Скорпион",
      "symbol": "♏",
      "dates": "23 октября – 21 ноября",
      "description": "Страстный, целеустремлённый, интуитивный",
      "color": "#9C27B0"
    },
    {
      "id": "sagittarius",
      "name": "Стрелец",
      "symbol": "♐",
      "dates": "22 ноября – 21 декабря",
      "description": "Оптимистичный, свободолюбивый, философский",
      "color": "#3F51B5"
    },
    {
      "id": "capricorn",
      "name": "Козерог",
      "symbol": "♑",
      "dates": "22 декабря – 19 января",
      "description": "Ответственный, дисциплинированный, амбициозный",
      "color": "#795548"
    },
    {
      "id": "aquarius",
      "name": "Водолей",
      "symbol": "♒",
      "dates": "20 января – 18 февраля",
      "description": "Инновационный, независимый, гуманитарный",
      "color": "#00BCD4"
    },
    {
      "id": "pisces",
      "name": "Рыбы",
      "symbol": "♓",
      "dates": "19 февраля – 20 марта",
      "description": "Чувствительный, творческий, эмпатичный",
      "color": "#673AB7"
    }
  ]
}